simsets/__init__.py
simsets-0.0.5.dist-info/DESCRIPTION.rst
simsets-0.0.5.dist-info/METADATA
simsets-0.0.5.dist-info/RECORD
simsets-0.0.5.dist-info/WHEEL
simsets-0.0.5.dist-info/metadata.json
simsets-0.0.5.dist-info/top_level.txt
