Metadata-Version: 2.0
Name: simsets
Version: 0.0.5
Summary: Create simulated datasets from original datasets
Home-page: http://github.com/staeiou/simsets
Author: Stuart Geiger
Author-email: stuart@stuartgeiger.com
License: MIT
Platform: UNKNOWN
Requires-Dist: numpy
Requires-Dist: pandas
